upgraded_cmd/__init__.py
upgraded_cmd/constants.py
upgraded_cmd/classes/__init__.py
upgraded_cmd/classes/cmd.py
upgraded_cmd/classes/entry.py
upgraded_cmd/classes/prompt.py
upgraded_cmd-1.1.2.dist-info/LICENSE
upgraded_cmd-1.1.2.dist-info/METADATA
upgraded_cmd-1.1.2.dist-info/WHEEL
upgraded_cmd-1.1.2.dist-info/top_level.txt
upgraded_cmd-1.1.2.dist-info/RECORD
