Metadata-Version: 2.1
Name: upgraded_cmd
Version: 1.1.2
Summary: Similar to built-in.cmd but allows tab completion in windows
Author: Loïc Chevalier
License-File: LICENSE
